apb_extra_utils/__init__.py
apb_extra_utils/excel_utils.py
apb_extra_utils/github.py
apb_extra_utils/logging.conf.yml
apb_extra_utils/misc.py
apb_extra_utils/png2svg.py
apb_extra_utils/send_mail.py
apb_extra_utils/utils_logging.py
apb_extra_utils/xml_xpath_parser.py
apb_extra_utils/ddl_to_scd/__init__.py
apb_extra_utils/ddl_to_scd/ddl_to_scd.py
apb_extra_utils/ddl_to_scd/template_base_SCD4.sql
apb_extra_utils/ddl_to_scd/template_base_SCD4C.sql
apb_extra_utils/postgres_pckg/__init__.py
apb_extra_utils/postgres_pckg/psql_alchemy.py
apb_extra_utils/sql_parser/__init__.py
apb_extra_utils/sql_parser/x_grouping.py
apb_extra_utils/sql_parser/x_sql_parser.py
apb_extra_utils-1.0.2.dist-info/METADATA
apb_extra_utils-1.0.2.dist-info/WHEEL
apb_extra_utils-1.0.2.dist-info/top_level.txt
apb_extra_utils-1.0.2.dist-info/RECORD
